cenao/__init__.py
cenao/app.py
cenao/config.py
cenao/errors.py
cenao/exceptions.py
cenao/runner.py
cenao/version.py
cenao/view.py
cenao/features/__init__.py
cenao/features/health.py
cenao/features/redis.py
cenao/features/s3.py
cenao/features/web.py
cenao/features/redis_storage/__init__.py
cenao/features/redis_storage/app_feature.py
cenao/features/redis_storage/model.py
cenao-0.12.3.dist-info/LICENSE
cenao-0.12.3.dist-info/METADATA
cenao-0.12.3.dist-info/WHEEL
cenao-0.12.3.dist-info/top_level.txt
cenao-0.12.3.dist-info/RECORD
